{
  "scenarios": [
    {
      "name": "15 Drone Complex 3D Scenario (400x400)",
      "primary_mission": {
        "drone_model": "DJI_Mavic_4_Pro",
        "start_time": 0,
        "end_time": 300,
        "waypoints": [
          { "x": 20, "y": 200, "z": 150 },
          { "x": 380, "y": 200, "z": 150 }
        ]
      },
      "simulated_flights": [
        {
          "flight_id": "Spiral_Ascent_1",
          "waypoints": [
            {"x": 40, "y": 40, "z": 10}, {"x": 50, "y": 45, "z": 20}, {"x": 40, "y": 50, "z": 30}, {"x": 30, "y": 45, "z": 40},
            {"x": 40, "y": 40, "z": 50}, {"x": 50, "y": 45, "z": 60}, {"x": 40, "y": 50, "z": 70}, {"x": 30, "y": 45, "z": 80},
            {"x": 40, "y": 40, "z": 90}, {"x": 50, "y": 45, "z": 100}
          ],
          "timestamps": [0, 10, 20, 30, 40, 50, 60, 70, 80, 90]
        },
        {
          "flight_id": "Box_Patrol_1",
          "waypoints": [
            {"x": 100, "y": 100, "z": 100}, {"x": 140, "y": 100, "z": 100}, {"x": 140, "y": 140, "z": 100}, {"x": 100, "y": 140, "z": 100},
            {"x": 100, "y": 100, "z": 120}, {"x": 140, "y": 100, "z": 120}, {"x": 140, "y": 140, "z": 120}, {"x": 100, "y": 140, "z": 120},
            {"x": 100, "y": 100, "z": 140}, {"x": 140, "y": 100, "z": 140}
          ],
          "timestamps": [5, 15, 25, 35, 45, 55, 65, 75, 85, 95]
        },
        {
          "flight_id": "Vertical_ZigZag_1",
          "waypoints": [
            {"x": 180, "y": 60, "z": 20}, {"x": 190, "y": 70, "z": 40}, {"x": 180, "y": 60, "z": 60}, {"x": 190, "y": 70, "z": 80},
            {"x": 180, "y": 60, "z": 100}, {"x": 190, "y": 70, "z": 120}, {"x": 180, "y": 60, "z": 140}, {"x": 190, "y": 70, "z": 160},
            {"x": 180, "y": 60, "z": 180}, {"x": 190, "y": 70, "z": 200}
          ],
          "timestamps": [0, 10, 20, 30, 40, 50, 60, 70, 80, 90]
        },
        {
          "flight_id": "Fast_Mover_1",
          "waypoints": [
            {"x": 240, "y": 20, "z": 200}, {"x": 240, "y": 60, "z": 190}, {"x": 240, "y": 100, "z": 180}, {"x": 240, "y": 140, "z": 170},
            {"x": 240, "y": 180, "z": 160}, {"x": 240, "y": 220, "z": 150}, {"x": 240, "y": 260, "z": 140}, {"x": 240, "y": 300, "z": 130},
            {"x": 240, "y": 340, "z": 120}, {"x": 240, "y": 380, "z": 110}
          ],
          "timestamps": [10, 18, 26, 34, 42, 50, 58, 66, 74, 82]
        },
        {
          "flight_id": "Slow_Survey_1",
          "waypoints": [
            {"x": 300, "y": 300, "z": 300}, {"x": 310, "y": 300, "z": 300}, {"x": 310, "y": 310, "z": 300}, {"x": 300, "y": 310, "z": 300},
            {"x": 300, "y": 300, "z": 300}, {"x": 310, "y": 300, "z": 300}, {"x": 310, "y": 310, "z": 300}, {"x": 300, "y": 310, "z": 300},
            {"x": 300, "y": 300, "z": 300}, {"x": 310, "y": 300, "z": 300}
          ],
          "timestamps": [0, 10, 20, 30, 40, 50, 60, 70, 80, 90]
        },
        {
          "flight_id": "Boundary_Check_1",
           "waypoints": [
            {"x": 360, "y": 40, "z": 50}, {"x": 360, "y": 360, "z": 50}, {"x": 380, "y": 360, "z": 50}, {"x": 380, "y": 40, "z": 50},
            {"x": 360, "y": 40, "z": 50}, {"x": 360, "y": 360, "z": 50}, {"x": 380, "y": 360, "z": 50}, {"x": 380, "y": 40, "z": 50},
            {"x": 360, "y": 40, "z": 50}, {"x": 380, "y": 40, "z": 50}
          ],
          "timestamps": [10, 25, 30, 45, 50, 65, 70, 85, 90, 95]
        },
        {
          "flight_id": "High_Altitude_Pass_1",
          "waypoints": [
            {"x": 20, "y": 160, "z": 400}, {"x": 60, "y": 160, "z": 400}, {"x": 100, "y": 160, "z": 400}, {"x": 140, "y": 160, "z": 400},
            {"x": 180, "y": 160, "z": 400}, {"x": 220, "y": 160, "z": 400}, {"x": 260, "y": 160, "z": 400}, {"x": 300, "y": 160, "z": 400},
            {"x": 340, "y": 160, "z": 400}, {"x": 380, "y": 160, "z": 400}
          ],
          "timestamps": [0, 10, 20, 30, 40, 50, 60, 70, 80, 90]
        },
        {
          "flight_id": "Low_Altitude_Dash_1",
          "waypoints": [
            {"x": 380, "y": 240, "z": 25}, {"x": 340, "y": 240, "z": 25}, {"x": 300, "y": 240, "z": 25}, {"x": 260, "y": 240, "z": 25},
            {"x": 220, "y": 240, "z": 25}, {"x": 180, "y": 240, "z": 25}, {"x": 140, "y": 240, "z": 25}, {"x": 100, "y": 240, "z": 25},
            {"x": 60, "y": 240, "z": 25}, {"x": 20, "y": 240, "z": 25}
          ],
          "timestamps": [5, 15, 25, 35, 45, 55, 65, 75, 85, 95]
        },
        {
          "flight_id": "Spiral_Descent_2",
          "waypoints": [
            {"x": 50, "y": 340, "z": 300}, {"x": 60, "y": 345, "z": 280}, {"x": 50, "y": 350, "z": 260}, {"x": 40, "y": 345, "z": 240},
            {"x": 50, "y": 340, "z": 220}, {"x": 60, "y": 345, "z": 200}, {"x": 50, "y": 350, "z": 180}, {"x": 40, "y": 345, "z": 160},
            {"x": 50, "y": 340, "z": 140}, {"x": 60, "y": 345, "z": 120}
          ],
          "timestamps": [101, 111, 121, 131, 141, 151, 161, 171, 181, 191]
        },
        {
          "flight_id": "Box_Patrol_2",
          "waypoints": [
            {"x": 110, "y": 310, "z": 150}, {"x": 150, "y": 310, "z": 150}, {"x": 150, "y": 350, "z": 150}, {"x": 110, "y": 350, "z": 150},
            {"x": 110, "y": 310, "z": 170}, {"x": 150, "y": 310, "z": 170}, {"x": 150, "y": 350, "z": 170}, {"x": 110, "y": 350, "z": 170},
            {"x": 110, "y": 310, "z": 190}, {"x": 150, "y": 310, "z": 190}
          ],
          "timestamps": [110, 125, 140, 155, 170, 185, 200, 215, 230, 245]
        },
        {
          "flight_id": "Vertical_ZigZag_2",
          "waypoints": [
            {"x": 190, "y": 270, "z": 30}, {"x": 200, "y": 280, "z": 60}, {"x": 190, "y": 270, "z": 90}, {"x": 200, "y": 280, "z": 120},
            {"x": 190, "y": 270, "z": 150}, {"x": 200, "y": 280, "z": 180}, {"x": 190, "y": 270, "z": 210}, {"x": 200, "y": 280, "z": 240},
            {"x": 190, "y": 270, "z": 270}, {"x": 200, "y": 280, "z": 300}
          ],
          "timestamps": [120, 135, 150, 165, 180, 195, 210, 225, 240, 255]
        },
        {
          "flight_id": "Fast_Mover_2",
          "waypoints": [
            {"x": 250, "y": 30, "z": 250}, {"x": 250, "y": 70, "z": 240}, {"x": 250, "y": 110, "z": 230}, {"x": 250, "y": 150, "z": 220},
            {"x": 250, "y": 190, "z": 210}, {"x": 250, "y": 230, "z": 200}, {"x": 250, "y": 270, "z": 190}, {"x": 250, "y": 310, "z": 180},
            {"x": 250, "y": 350, "z": 170}, {"x": 250, "y": 390, "z": 160}
          ],
          "timestamps": [150, 160, 170, 180, 190, 200, 210, 220, 230, 240]
        },
        {
          "flight_id": "Slow_Survey_2",
          "waypoints": [
            {"x": 310, "y": 100, "z": 350}, {"x": 320, "y": 100, "z": 350}, {"x": 320, "y": 110, "z": 350}, {"x": 310, "y": 110, "z": 350},
            {"x": 310, "y": 100, "z": 350}, {"x": 320, "y": 100, "z": 350}, {"x": 320, "y": 110, "z": 350}, {"x": 310, "y": 110, "z": 350},
            {"x": 310, "y": 100, "z": 350}, {"x": 320, "y": 100, "z": 350}
          ],
          "timestamps": [200, 210, 220, 230, 240, 250, 260, 270, 280, 290]
        },
        {
          "flight_id": "Boundary_Check_2",
          "waypoints": [
            {"x": 370, "y": 50, "z": 75}, {"x": 370, "y": 370, "z": 75}, {"x": 390, "y": 370, "z": 75}, {"x": 390, "y": 50, "z": 75},
            {"x": 370, "y": 50, "z": 75}, {"x": 370, "y": 370, "z": 75}, {"x": 390, "y": 370, "z": 75}, {"x": 390, "y": 50, "z": 75},
            {"x": 370, "y": 50, "z": 75}, {"x": 390, "y": 50, "z": 75}
          ],
          "timestamps": [180, 200, 205, 225, 230, 250, 255, 275, 280, 285]
        },
        {
          "flight_id": "High_Altitude_Pass_2",
          "waypoints": [
            {"x": 30, "y": 360, "z": 450}, {"x": 70, "y": 360, "z": 450}, {"x": 110, "y": 360, "z": 450}, {"x": 150, "y": 360, "z": 450},
            {"x": 190, "y": 360, "z": 450}, {"x": 230, "y": 360, "z": 450}, {"x": 270, "y": 360, "z": 450}, {"x": 310, "y": 360, "z": 450},
            {"x": 350, "y": 360, "z": 450}, {"x": 390, "y": 360, "z": 450}
          ],
          "timestamps": [200, 210, 220, 230, 240, 250, 260, 270, 280, 290]
        }
      ]
    }
  ]
}
